xapi/__init__.py
xapi/actions.py
xapi/constants.py
xapi/helpers.py
xapi/log.py
xapi/modules/__init__.py
xapi/modules/base.py
xapi/modules/follow.py
xapi/modules/followers.py
xapi/modules/following.py
xapi/modules/helpers.py
xapi/modules/home_timeline.py
xapi/modules/like.py
xapi/modules/login.py
xapi/modules/notifications.py
xapi/modules/read_dms.py
xapi/modules/search.py
xapi/modules/send_dm.py
xapi/modules/unfollow.py
xapi/modules/user.py
xapi/modules/user_tweet_replies.py
xapi/modules/user_tweets.py
xapi/modules/verified_followers.py
xapi/modules/x.py
xapi/x_session.py
xtwitterapi-1.0.1.dist-info/METADATA
xtwitterapi-1.0.1.dist-info/WHEEL
xtwitterapi-1.0.1.dist-info/RECORD
