Metadata-Version: 2.1
Name: xtwitterapi
Version: 1.0.1
Summary: Unofficial X API client. Follow, Like, DM, Search and other actions.
License: MIT
Author: TadasG
Author-email: no@email.com
Requires-Python: >=3.10,<4.0
Classifier: License :: OSI Approved :: MIT License
Classifier: Programming Language :: Python :: 3
Classifier: Programming Language :: Python :: 3.10
Classifier: Programming Language :: Python :: 3.11
Classifier: Programming Language :: Python :: 3.12
Requires-Dist: beautifulsoup4 (>=4.12.3,<5.0.0)
Requires-Dist: curl-cffi (>=0.7.4,<0.8.0)
Requires-Dist: lxml (>=5.3.0,<6.0.0)
Requires-Dist: pydantic (>=2.9.2,<3.0.0)
Requires-Dist: structlog (>=24.4.0,<25.0.0)
